<?xml version="1.0" encoding="UTF-8" standalone="no"?>
<annotation>
    <folder>NA</folder>
    <filename>b097_1580797703543.jpg</filename>
    <source>
        <database>Unknown</database>
    </source>
    <size>
        <width>500</width>
        <height>343</height>
        <depth>3</depth>
    </size>
    <segmented>0</segmented>
    <object>
        <name>no_mask</name>
        <pose>Unspecified</pose>
        <truncated>0</truncated>
        <difficult>0</difficult>
        <occluded>0</occluded>
        <bndbox>
            <xmin>15</xmin>
            <ymin>90</ymin>
            <xmax>53</xmax>
            <ymax>147</ymax>
        </bndbox>
    </object>
    <object>
        <name>no_mask</name>
        <pose>Unspecified</pose>
        <truncated>0</truncated>
        <difficult>0</difficult>
        <occluded>0</occluded>
        <bndbox>
            <xmin>49</xmin>
            <ymin>73</ymin>
            <xmax>92</xmax>
            <ymax>125</ymax>
        </bndbox>
    </object>
    <object>
        <name>no_mask</name>
        <pose>Unspecified</pose>
        <truncated>0</truncated>
        <difficult>0</difficult>
        <occluded>0</occluded>
        <bndbox>
            <xmin>97</xmin>
            <ymin>68</ymin>
            <xmax>141</xmax>
            <ymax>123</ymax>
        </bndbox>
    </object>
    <object>
        <name>no_mask</name>
        <pose>Unspecified</pose>
        <truncated>0</truncated>
        <difficult>0</difficult>
        <occluded>0</occluded>
        <bndbox>
            <xmin>158</xmin>
            <ymin>70</ymin>
            <xmax>193</xmax>
            <ymax>114</ymax>
        </bndbox>
    </object>
    <object>
        <name>no_mask</name>
        <pose>Unspecified</pose>
        <truncated>0</truncated>
        <difficult>0</difficult>
        <occluded>0</occluded>
        <bndbox>
            <xmin>184</xmin>
            <ymin>68</ymin>
            <xmax>234</xmax>
            <ymax>118</ymax>
        </bndbox>
    </object>
    <object>
        <name>no_mask</name>
        <pose>Unspecified</pose>
        <truncated>0</truncated>
        <difficult>0</difficult>
        <occluded>0</occluded>
        <bndbox>
            <xmin>289</xmin>
            <ymin>105</ymin>
            <xmax>328</xmax>
            <ymax>152</ymax>
        </bndbox>
    </object>
    <object>
        <name>no_mask</name>
        <pose>Unspecified</pose>
        <truncated>0</truncated>
        <difficult>0</difficult>
        <occluded>0</occluded>
        <bndbox>
            <xmin>349</xmin>
            <ymin>77</ymin>
            <xmax>392</xmax>
            <ymax>129</ymax>
        </bndbox>
    </object>
    <object>
        <name>no_mask</name>
        <pose>Unspecified</pose>
        <truncated>0</truncated>
        <difficult>0</difficult>
        <occluded>0</occluded>
        <bndbox>
            <xmin>392</xmin>
            <ymin>52</ymin>
            <xmax>437</xmax>
            <ymax>105</ymax>
        </bndbox>
    </object>
</annotation>
